stochss_compute/__init__.py
stochss_compute/__version__.py
stochss_compute/compute_server.py
stochss_compute/launch.py
stochss_compute/remote_results.py
stochss_compute/remote_simulation.py
stochss_compute/remote_utils.py
stochss_compute/api/__init__.py
stochss_compute/api/api.py
stochss_compute/api/cache/__init__.py
stochss_compute/api/cache/cache_provider.py
stochss_compute/api/cache/simple_disk_cache.py
stochss_compute/api/delegate/__init__.py
stochss_compute/api/delegate/dask_delegate.py
stochss_compute/api/delegate/delegate.py
stochss_compute/api/delegate/redis_namespace.py
stochss_compute/api/v1/__init__.py
stochss_compute/api/v1/apiutils.py
stochss_compute/api/v1/dataclass.py
stochss_compute/api/v1/job.py
stochss_compute/api/v1/memory.py
stochss_compute/api/v1/gillespy2/__init__.py
stochss_compute/api/v1/gillespy2/dataclass.py
stochss_compute/api/v1/gillespy2/model.py
stochss_compute/api/v1/gillespy2/results.py
stochss_compute/client/__init__.py
stochss_compute/client/compute_server.py
stochss_compute/client/endpoint.py
stochss_compute/client/server.py
stochss_compute/cloud/__init__.py
stochss_compute/cloud/ec2.py
stochss_compute/cloud/ec2_config.py
stochss_compute/cloud/exceptions.py
stochss_compute/core/__init__.py
stochss_compute/core/errors.py
stochss_compute/core/messages.py
stochss_compute/core/remote_results.py
stochss_compute/core/remote_simulation.py
stochss_compute/server/__init__.py
stochss_compute/server/api.py
stochss_compute/server/cache.py
stochss_compute/server/is_cached.py
stochss_compute/server/results.py
stochss_compute/server/run.py
stochss_compute/server/sourceip.py
stochss_compute/server/status.py
test/__init__.py
test/run_integration_tests.py
test/run_system_tests.py
test/run_unit_tests.py
test/integration_tests/__init__.py
test/integration_tests/gillespy2_models.py
test/integration_tests/test_cache.py
test/system_tests/__init__.py
test/system_tests/gillespy2_models.py
test/system_tests/test_cli.py
test/system_tests/test_launch_cli.py
stochss_compute-1.0.2.dist-info/LICENSE.md
stochss_compute-1.0.2.dist-info/METADATA
stochss_compute-1.0.2.dist-info/WHEEL
stochss_compute-1.0.2.dist-info/entry_points.txt
stochss_compute-1.0.2.dist-info/top_level.txt
stochss_compute-1.0.2.dist-info/RECORD
