Metadata-Version: 2.1
Name: stochss-compute
Version: 1.0.2
Summary: A compute delegation package for the StochSS family of stochastic simulators
Home-page: https://github.com/StochSS/stochss-compute
Author: See CONTRIBUTORS.md
Author-email: briandrawert@gmail.com
License: GPLv3
Platform: UNKNOWN
Classifier: Development Status :: 5 - Production/Stable
Classifier: License :: OSI Approved :: GNU General Public License v3 (GPLv3)
Classifier: Operating System :: OS Independent
Classifier: Programming Language :: Python :: 3
Classifier: Topic :: Scientific/Engineering
Classifier: Topic :: Scientific/Engineering :: Chemistry
Classifier: Topic :: Scientific/Engineering :: Mathematics
Classifier: Topic :: Scientific/Engineering :: Medical Science Apps.
Classifier: Intended Audience :: Science/Research
Requires-Dist: distributed (==2022.12.1)
Requires-Dist: filelock (==3.9.0)
Requires-Dist: gillespy2 (>=1.8.2)
Requires-Dist: requests (==2.28.1)
Provides-Extra: aws
Requires-Dist: boto3 (==1.24.71) ; extra == 'aws'
Requires-Dist: paramiko (==2.11.0) ; extra == 'aws'
Requires-Dist: python-dotenv (==0.21.0) ; extra == 'aws'
Provides-Extra: dev
Requires-Dist: coverage ; extra == 'dev'
Requires-Dist: moto ; extra == 'dev'
